Grid_Txt_Package/__init__.py
Skylark_Grid/__init__.py
Skylark_Grid-0.3.dist-info/METADATA
Skylark_Grid-0.3.dist-info/WHEEL
Skylark_Grid-0.3.dist-info/top_level.txt
Skylark_Grid-0.3.dist-info/RECORD
