Metadata-Version: 2.1
Name: Skylark-Grid
Version: 0.3
Summary: An image grid maker tool
Author: Prem Varma
Author-email: prem.varma@skylarklabs.ai
License: UNKNOWN
Platform: UNKNOWN
Requires-Dist: opencv-python
Requires-Dist: numpy
